{
  "layout": {
    "actions": {
      "lesson_form_create": {
        "header": {
          "assets": {
            "0": {
              "tagit_css": {
                "type": "css",
                "file": "jquery.tagit.css"
              },
              "zendesk_css": {
                "type": "css",
                "file": "tagit.ui-zendesk.css"
              },
              "jquery_ui": {
                "type": "jquery",
                "file": "https://ajax.googleapis.com/ajax/libs/jqueryui/1.9.2/jquery-ui.min.js"
              },
              "tagit_js": {
                "type": "js",
                "file": "js/tag-it.js"
              },
              "form_css": {
                "type": "css",
                "file": "form_css.css"
              },
              "form_js": {
                "type": "js",
                "file": "js/form_js.js"
              }
            }
          }
        },
        "content": {
          "type": "page/view",
          "template": "App/Lesson/View/Template/Create.phtml"
        }
      },
      "lesson_form_edit": {
        "header": {
          "assets": {
            "0": {
              "tagit_css": {
                "type": "css",
                "file": "jquery.tagit.css"
              },
              "zendesk_css": {
                "type": "css",
                "file": "tagit.ui-zendesk.css"
              },
              "jquery_ui": {
                "type": "jquery",
                "file": "https://ajax.googleapis.com/ajax/libs/jqueryui/1.9.2/jquery-ui.min.js"
              },
              "tagit_js": {
                "type": "js",
                "file": "js/tag-it.js"
              },
              "form_css": {
                "type": "css",
                "file": "form_css.css"
              },
              "form_js": {
                "type": "js",
                "file": "js/form_js.js"
              }
            }
          }
        },
        "content": {
          "type": "page/view",
          "template": "App/Lesson/View/Template/Edit.phtml"
        }
      },
      "lesson_form_event": {
      "header": {
        "assets": {
          "0": {
            "tagit_css": {
              "type": "css",
              "file": "jquery.tagit.css"
            },
            "zendesk_css": {
              "type": "css",
              "file": "tagit.ui-zendesk.css"
            },
            "jquery_ui": {
              "type": "jquery",
              "file": "https://code.jquery.com/ui/1.11.4/jquery-ui.min.js"
            },
            "tagit_js": {
              "type": "js",
              "file": "js/tag-it.js"
            },
            "student_js": {
              "type": "js",
              "file": "js/student_js.js"
            },
            "form_js": {
              "type": "js",
              "file": "js/form_js.js"
            },
            "form_css": {
              "type": "css",
              "file": "form_css.css"
            },
            "datepicker_css": {
              "type": "css",
              "file": "datepicker.almost-flat.css"
            },
            "datepicker_js": {
              "type": "js",
              "file": "js/components/datepicker.js"
            },
            "autocomplete_css": {
              "type": "css",
              "file": "autocomplete.almost-flat.css"
            },
            "autocomplete_js": {
              "type": "js",
              "file": "js/components/autocomplete.js"
            },
            "timpicker_js": {
              "type": "js",
              "file": "js/components/timepicker.js"
            }
          }
        }
      },
      "content": {
        "type": "page/view",
        "template": "App/Lesson/View/Template/Schedule.phtml"
      }
    },
      "lesson_view_id": {
        "content" : {
            "type": "page/view",
            "template" : "App/Lesson/View/Template/Lesson.phtml"
        }
      },
      "lesson_view_index" : {
            "content" : {
              "type" : "page/view",
              "template": "App/Lesson/View/Template/Index.phtml"
            }
        }
    }
  }
}